{
    "videoId": "3BMnsn7J7j8",
    "channelId": "UCttspZesZIDEwwpVIgoZtWQ",
    "title": "Demonetisation: What Happen When Banks will Remain Closed for Three Days",
    "channelTitle": "IndiaTV",
    "description": "Demonetisation: What happen when banks will remain closed in many places for three days. Most of the ATMs are already cashless. \nHundreds of crore cash which include old Rs 500 and Rs 1000 notes and new Rs 2000 notes have been seized in the raids by Income tax department across the country while people are standing in queues outside banks and ATMs. Many corrupt bank employees have been suspended and transferred for converting black money into white.\n\nSUBSCRIBE to India TV Here: http://goo.gl/fcdXM0\n\nFollow India TV on Social Media:\nFacebook: https://www.facebook.com/indiatvnews\nTwitter: https://twitter.com/indiatvnews\n\nDownload India TV Android App here: http://goo.gl/kOQvVB\n\nFor More Videos Visit Here:\nhttp://www.indiatvnews.com/video/",
    "thumbnails": {
        "default": {
            "url": "https://i.ytimg.com/vi/3BMnsn7J7j8/default.jpg",
            "width": 120,
            "height": 90
        },
        "high": {
            "url": "https://i.ytimg.com/vi/3BMnsn7J7j8/hqdefault.jpg",
            "width": 480,
            "height": 360
        },
        "medium": {
            "url": "https://i.ytimg.com/vi/3BMnsn7J7j8/mqdefault.jpg",
            "width": 320,
            "height": 180
        },
        "standard": {
            "url": "https://i.ytimg.com/vi/3BMnsn7J7j8/sddefault.jpg",
            "width": 640,
            "height": 480
        }
    },
    "tags": [
        "rs 500",
        "rs 1000",
        "demonetisation",
        "note ban",
        "black money",
        "rs 500 and rs 1000",
        "rs 2000",
        "income tax raid",
        "PM Modi",
        "currency ban",
        "queue outside ATMs",
        "cash in ATMs",
        "cash withdrawal",
        "cashless economy",
        "platic money",
        "hindi news",
        "India TV",
        "india tv news",
        "india tv live",
        "india tv news live",
        "india tv hindi",
        "india tv youtube",
        "india tv hindi news",
        "india tv channel live"
    ],
    "categoryId": 25,
    "viewCount": 1935,
    "likeCount": 6,
    "dislikeCount": 3,
    "relevantKeywords": [
        "demonetisation",
        "happen",
        "banks",
        "remain",
        "closed",
        "three",
        "days",
        "indiatv",
        "many",
        "places",
        "atms",
        "already",
        "cashless",
        "hundreds",
        "crore",
        "cash",
        "include",
        "old",
        "rs",
        "500",
        "1000",
        "notes",
        "new",
        "2000",
        "seized",
        "raids",
        "income",
        "tax",
        "department",
        "across",
        "country",
        "people",
        "standing",
        "queues",
        "outside",
        "corrupt",
        "bank",
        "employees",
        "suspended",
        "transferred",
        "converting",
        "black",
        "money",
        "white",
        "subscribe",
        "india",
        "tv",
        "follow",
        "social",
        "media",
        "facebook",
        "twitter",
        "download",
        "android",
        "app",
        "videos",
        "visit"
    ]
}