{
    "videoId": "4qL2juN58uU",
    "channelId": "UCZFMm1mMw0F81Z37aaEzTUA",
    "title": "On Notes Ban, Supreme Court Says 5 Judges To Decide If It's Legally Valid",
    "channelTitle": "NDTV",
    "description": "Five senior most judges will decide whether the notes ban is legal and whether it is a violation of fundamental rights, the Supreme Court said today. The court is hearing petitions challenging the ban on 500 and 1,000 rupee notes last month, which has left millions facing a cash crunch and scrambling to banks and ATMs.\n\n\nWatch more videos: http://www.ndtv.com/video?yt\nDownload the NDTV news app: https://play.google.com/store/apps/details?id=com.july.ndtv&utm_source=Youtube&utm_medium=embed&utm_campaign=Inhouse_App_Install",
    "thumbnails": {
        "default": {
            "url": "https://i.ytimg.com/vi/4qL2juN58uU/default.jpg",
            "width": 120,
            "height": 90
        },
        "high": {
            "url": "https://i.ytimg.com/vi/4qL2juN58uU/hqdefault.jpg",
            "width": 480,
            "height": 360
        },
        "medium": {
            "url": "https://i.ytimg.com/vi/4qL2juN58uU/mqdefault.jpg",
            "width": 320,
            "height": 180
        }
    },
    "tags": [
        "Demonetisation",
        "Supreme Court",
        "PM Modi",
        "ndtv 24x7",
        "constitutional bench",
        "rs 500",
        "rs 1000",
        "note ban",
        "currency ban",
        "supreme",
        "court",
        "refused",
        "interfere",
        "centre",
        "policy",
        "monetization",
        "stage",
        "however",
        "five",
        "judge",
        "constitution",
        "bench",
        "decide",
        "note",
        "ban",
        "legal",
        "whether",
        "violates",
        "fundamental",
        "rights",
        "also",
        "going",
        "look",
        "judiciary",
        "fiscal",
        "joining",
        "us",
        "bit",
        "mr",
        "subramaniyam",
        "arguing",
        "behalf",
        "government",
        "particular",
        "case",
        "today",
        "really",
        "thank",
        "actually",
        "clarification",
        "would",
        "seeking",
        "assuming",
        "end",
        "process",
        "man",
        "done",
        "eighty",
        "percent",
        "notes",
        "already",
        "redeposited",
        "br",
        "know",
        "month",
        "exactly",
        "happen",
        "even",
        "take",
        "decision",
        "well",
        "far",
        "issue",
        "concerned",
        "matter",
        "sub",
        "judice",
        "improper",
        "point",
        "time",
        "make",
        "comment",
        "show",
        "right",
        "specifically",
        "happening",
        "taken",
        "cases",
        "high",
        "says",
        "alone",
        "question",
        "legality",
        "sort",
        "exemptions",
        "made",
        "violation",
        "yes",
        "frame",
        "nine",
        "questions",
        "consideration",
        "judges",
        "felt",
        "issues",
        "reaching",
        "implications",
        "importance",
        "country",
        "therefore",
        "decided",
        "could",
        "proper",
        "range",
        "timeline",
        "think",
        "come",
        "band",
        "learner",
        "attorney",
        "general",
        "submitted",
        "initial",
        "arguments",
        "first",
        "codes",
        "power",
        "extremely",
        "limited",
        "judicial",
        "review",
        "physical",
        "one",
        "honourable",
        "framed",
        "adjudication",
        "timeframe",
        "issued",
        "notice",
        "writ",
        "petitions",
        "reply",
        "filed",
        "within",
        "six",
        "weeks",
        "thereafter",
        "rejoined",
        "er",
        "petitioners",
        "another",
        "three",
        "definitely",
        "fact",
        "position",
        "hear",
        "gets",
        "constituted"
    ],
    "categoryId": 25,
    "viewCount": 2497,
    "likeCount": 12,
    "dislikeCount": 1,
    "relevantKeywords": [
        "notes",
        "ban",
        "supreme",
        "court",
        "says",
        "judges",
        "decide",
        "legally",
        "valid",
        "ndtv",
        "five",
        "senior",
        "whether",
        "legal",
        "violation",
        "fundamental",
        "rights",
        "said",
        "today",
        "hearing",
        "petitions",
        "challenging",
        "500",
        "000",
        "rupee",
        "last",
        "month",
        "left",
        "millions",
        "facing",
        "cash",
        "crunch",
        "scrambling",
        "banks",
        "atms",
        "watch",
        "videos",
        "download",
        "news",
        "app",
        "demonetisation",
        "pm",
        "modi",
        "24x7",
        "constitutional",
        "bench",
        "rs",
        "1000",
        "note",
        "currency",
        "refused",
        "interfere",
        "centre",
        "policy",
        "monetization",
        "stage",
        "however",
        "judge",
        "constitution",
        "violates",
        "also",
        "going",
        "look",
        "judiciary",
        "fiscal",
        "joining",
        "us",
        "bit",
        "mr",
        "subramaniyam",
        "arguing",
        "behalf",
        "government",
        "particular",
        "case",
        "really",
        "thank",
        "actually",
        "clarification",
        "would",
        "seeking",
        "assuming",
        "end",
        "process",
        "man",
        "done",
        "eighty",
        "percent",
        "already",
        "redeposited",
        "br",
        "know",
        "exactly",
        "happen",
        "even",
        "take",
        "decision",
        "well",
        "far",
        "issue",
        "concerned",
        "matter",
        "sub",
        "judice",
        "improper",
        "point",
        "time",
        "make",
        "comment",
        "show",
        "right",
        "specifically",
        "happening",
        "taken",
        "cases",
        "high",
        "alone",
        "question",
        "legality",
        "sort",
        "exemptions",
        "made",
        "yes",
        "frame",
        "nine",
        "questions",
        "consideration",
        "felt",
        "issues",
        "reaching",
        "implications",
        "importance",
        "country",
        "therefore",
        "decided",
        "could",
        "proper",
        "range",
        "timeline",
        "think",
        "come",
        "band",
        "learner",
        "attorney",
        "general",
        "submitted",
        "initial",
        "arguments",
        "first",
        "codes",
        "power",
        "extremely",
        "limited",
        "judicial",
        "review",
        "physical",
        "one",
        "honourable",
        "framed",
        "adjudication",
        "timeframe",
        "issued",
        "notice",
        "writ",
        "reply",
        "filed",
        "within",
        "six",
        "weeks",
        "thereafter",
        "rejoined",
        "er",
        "petitioners",
        "another",
        "three",
        "definitely",
        "fact",
        "position",
        "hear",
        "gets",
        "constituted"
    ]
}