{
    "videoId": "6JOc4sr4wKk",
    "channelId": "UCZFMm1mMw0F81Z37aaEzTUA",
    "title": "Black Money Turns White: Why Economist Jagdish Bhagwati Says That's Good",
    "channelTitle": "NDTV",
    "description": "Around 37,000 crores have been deposited in Jan Dhan accounts since demonetisation. These deposits have raised concern of black money being laundered using these accounts. Renowned economist Jagdish Bhagwati however feels that's not a cause for concern as that money is benefitting the poor. Speaking to NDTV from Columbia University, Mr Bhagwati said don't call this corruption but treat it like an amnesty scheme.\n\nWatch more videos: http://www.ndtv.com/video?yt\nDownload the NDTV news app: https://play.google.com/store/apps/details?id=com.july.ndtv&utm_source=Youtube&utm_medium=embed&utm_campaign=Inhouse_App_Install",
    "thumbnails": {
        "default": {
            "url": "https://i.ytimg.com/vi/6JOc4sr4wKk/default.jpg",
            "width": 120,
            "height": 90
        },
        "high": {
            "url": "https://i.ytimg.com/vi/6JOc4sr4wKk/hqdefault.jpg",
            "width": 480,
            "height": 360
        },
        "medium": {
            "url": "https://i.ytimg.com/vi/6JOc4sr4wKk/mqdefault.jpg",
            "width": 320,
            "height": 180
        }
    },
    "tags": [
        "Jagdish Bhagwati",
        "Jan Dhan accounts",
        "black money",
        "Narendra Modi",
        "demonetisation",
        "Rs. 500 and 1000 notes banned",
        "Cash crisis",
        "cash crunch",
        "demonetisation impact",
        "The Buck Stops Here",
        "ndtv 24x7",
        "little",
        "month",
        "since",
        "prime",
        "minister",
        "modi",
        "announced",
        "decision",
        "monetize",
        "86",
        "currency",
        "circulation",
        "500",
        "1000",
        "rupee",
        "notes",
        "debate",
        "india",
        "rages",
        "master",
        "stroke",
        "misadventure",
        "joining",
        "us",
        "columbia",
        "university",
        "somebody",
        "course",
        "well",
        "respected",
        "economist",
        "also",
        "one",
        "foremost",
        "thinkers",
        "public",
        "intellectuals",
        "time",
        "professor",
        "ghibli",
        "geography",
        "bhagwati",
        "welcome",
        "program",
        "first",
        "asked",
        "big",
        "picture",
        "impression",
        "disruptive",
        "people",
        "called",
        "bold",
        "others",
        "said",
        "absolutely",
        "sense",
        "bad",
        "news",
        "economy",
        "see",
        "sir",
        "distinguish",
        "avoidable",
        "losses",
        "unavoidable",
        "may",
        "result",
        "like",
        "instance",
        "print",
        "large",
        "numbers",
        "going",
        "replacing",
        "thousand",
        "actually",
        "order",
        "huge",
        "things",
        "way",
        "could",
        "keep",
        "quiet",
        "bound",
        "know",
        "mean",
        "particular",
        "nothing",
        "kept",
        "secret",
        "long",
        "given",
        "start",
        "printing",
        "ahead",
        "leak",
        "create",
        "massive",
        "disruption",
        "um",
        "call",
        "transitional",
        "loss",
        "short",
        "run",
        "different",
        "something",
        "think",
        "measure",
        "taken",
        "coming",
        "government",
        "would",
        "come",
        "saying",
        "idea",
        "simply",
        "look",
        "wonder",
        "anybody",
        "looks",
        "degree",
        "care",
        "says",
        "promise",
        "pay",
        "recon",
        "arrests",
        "pointed",
        "wrong",
        "opinion",
        "amounts",
        "abrogation",
        "obligation",
        "take",
        "note",
        "back",
        "anywhere",
        "rbi",
        "wherever",
        "exchanged",
        "present",
        "give",
        "another",
        "cockeyed",
        "say",
        "sort",
        "talking",
        "violation",
        "right",
        "property",
        "go",
        "gon",
        "na",
        "indian",
        "constitution",
        "taught",
        "years",
        "amendment",
        "passed",
        "enable",
        "impound",
        "social",
        "cause",
        "sometimes",
        "taking",
        "pick",
        "piece",
        "necessary",
        "compensation",
        "point",
        "abolition",
        "person",
        "prep",
        "pretty",
        "versus",
        "princes",
        "struck",
        "gut",
        "supreme",
        "court",
        "kind",
        "notion",
        "somehow",
        "undemocratic",
        "seem",
        "make",
        "kinds",
        "criticisms",
        "view",
        "shoot",
        "hip",
        "problems",
        "worry",
        "let",
        "ask",
        "talk",
        "problematic",
        "seen",
        "data",
        "six",
        "percent",
        "black",
        "money",
        "estimated",
        "cash",
        "might",
        "period",
        "phase",
        "discomfort",
        "worth",
        "end",
        "achieve",
        "much",
        "fact",
        "pose",
        "problem",
        "trying",
        "masses",
        "hordes",
        "old",
        "mirrors",
        "lying",
        "used",
        "transact",
        "want",
        "sell",
        "house",
        "difficult",
        "demand",
        "return",
        "paint",
        "rather",
        "write",
        "prepared",
        "even",
        "structural",
        "difficulties",
        "eliminate",
        "possible",
        "holes",
        "holding",
        "swiss",
        "accounts",
        "abroad",
        "catch",
        "tell",
        "foreign",
        "light",
        "whether",
        "names",
        "directly",
        "put",
        "yeah",
        "supposing",
        "name",
        "wikileaks",
        "easier",
        "done",
        "feeling",
        "margin",
        "meaning",
        "additionally",
        "really",
        "originate",
        "better",
        "outflows",
        "already",
        "current",
        "bigger",
        "agree",
        "friend",
        "dr",
        "manmohan",
        "singh",
        "stood",
        "parliament",
        "shave",
        "least",
        "accept",
        "accurate",
        "assessment",
        "always",
        "based",
        "assumptions",
        "thing",
        "good",
        "mine",
        "doubtless",
        "criticize",
        "making",
        "assumption",
        "myra",
        "frank",
        "ideological",
        "congress",
        "party",
        "lost",
        "ways",
        "country",
        "united",
        "states",
        "democrats",
        "donald",
        "trump",
        "yes",
        "damnedest",
        "best",
        "sorts",
        "outcome",
        "accepted",
        "led",
        "monumental",
        "true",
        "member",
        "though",
        "wish",
        "fairly",
        "complicated",
        "issue",
        "interview",
        "study",
        "ramifications",
        "necessarily",
        "gotten",
        "certainly",
        "rushing",
        "pronouncements",
        "former",
        "rushed",
        "within",
        "province",
        "advice",
        "matter",
        "mr",
        "chidambaram",
        "hold",
        "high",
        "regard",
        "political",
        "types",
        "viewing",
        "grain",
        "salt",
        "calling",
        "makers",
        "example",
        "fair",
        "amount",
        "five",
        "hundred",
        "convert",
        "without",
        "bank",
        "detective",
        "servant",
        "rupees",
        "30",
        "scenario",
        "inactive",
        "aisle",
        "mirror",
        "become",
        "active",
        "poor",
        "guy",
        "guard",
        "real",
        "spend",
        "two",
        "effects",
        "redistribution",
        "rich",
        "laundering",
        "white",
        "happened",
        "judge",
        "sergeant",
        "deposits",
        "basically",
        "specific",
        "scheme",
        "ready",
        "beneficiaries",
        "means",
        "terms",
        "case",
        "around",
        "maybe",
        "transacted",
        "transactions",
        "activated",
        "spent",
        "expect",
        "expansionary",
        "effect",
        "deflationary",
        "still",
        "corruption",
        "getting",
        "rid",
        "road",
        "stock",
        "decimating",
        "far",
        "destructs",
        "loses",
        "fine",
        "amnesty",
        "schemes",
        "world",
        "bother",
        "okay",
        "banks",
        "monetization",
        "nearly",
        "12",
        "lakh",
        "crores",
        "value",
        "pi",
        "fourteen",
        "three",
        "overestimated",
        "system",
        "market",
        "parallel",
        "turn",
        "essentially",
        "object",
        "objecting",
        "universally",
        "tried",
        "contexts",
        "lot",
        "printed",
        "either",
        "brought",
        "leaking",
        "astonishing",
        "sphere",
        "15",
        "eleven",
        "half",
        "december",
        "converted",
        "sign",
        "success",
        "culture",
        "etcetera",
        "full",
        "speed",
        "agencies",
        "blast",
        "embarrass",
        "sabotage",
        "secrecy",
        "longer",
        "required",
        "destroys",
        "aim",
        "achieved",
        "exactly",
        "enables",
        "giving",
        "principal",
        "use",
        "help",
        "queue",
        "redistributive",
        "populism",
        "away",
        "wonderful",
        "oh",
        "four",
        "majority",
        "uprising",
        "test",
        "error",
        "sample",
        "survey",
        "happy",
        "benefiting",
        "democratic",
        "artists",
        "despotic",
        "clearly",
        "forget",
        "ji",
        "dan",
        "thourough",
        "politicians",
        "interruption",
        "statements",
        "option",
        "part",
        "circumspect",
        "fail",
        "biggest",
        "everything",
        "observed",
        "daily",
        "wage",
        "laborers",
        "suffering",
        "farmers",
        "labor",
        "works",
        "fields",
        "crunch",
        "small",
        "medium",
        "enterprises",
        "hurt",
        "report",
        "jobs",
        "hittin",
        "major",
        "hit",
        "worries",
        "implemented",
        "concerns",
        "implementation",
        "lack",
        "head",
        "delays",
        "able",
        "answer",
        "question",
        "sure",
        "pumped",
        "nandan",
        "nilekani",
        "compensate",
        "withdrawn",
        "smooth",
        "transition",
        "shortage",
        "secondly",
        "buy",
        "studied",
        "decades",
        "tend",
        "rush",
        "judgment",
        "export",
        "markets",
        "worried",
        "closed",
        "open",
        "crazy",
        "rules",
        "made",
        "available",
        "rapidly",
        "soon",
        "get",
        "bureaucrat",
        "decent",
        "bureaucrats",
        "consulted",
        "forte",
        "need",
        "man",
        "men",
        "practical",
        "experience",
        "women",
        "lived",
        "briefly",
        "governor",
        "ajit",
        "patel",
        "appointed",
        "among",
        "welcomed",
        "choice",
        "focus",
        "feel",
        "upfront",
        "visible",
        "speaking",
        "authority",
        "undermined",
        "critics",
        "today",
        "last",
        "thoughts",
        "comes",
        "background",
        "stupid",
        "wanted",
        "length",
        "inference",
        "suddenly",
        "came",
        "blue",
        "told",
        "economists",
        "driving",
        "force",
        "security",
        "pakistan",
        "possibly",
        "lots",
        "counterfeit",
        "apparently",
        "many",
        "friends",
        "ground",
        "blame",
        "smart",
        "jit",
        "moved",
        "quickly",
        "bit",
        "unfair",
        "got",
        "started",
        "tweaking",
        "trust",
        "fix",
        "arising",
        "america",
        "monday",
        "morning",
        "quarterbacking",
        "event",
        "ah",
        "thought",
        "policy",
        "consists",
        "infeasible",
        "art",
        "anticipating",
        "every",
        "move",
        "arise",
        "tweak",
        "income",
        "tax",
        "act",
        "november",
        "28th",
        "changes",
        "8th",
        "maker",
        "anticipate",
        "particularly",
        "gigantic",
        "undertaken",
        "develop",
        "mark",
        "poverty",
        "thinking",
        "guessing",
        "thumbs",
        "caused",
        "pleasure",
        "thank",
        "martha"
    ],
    "categoryId": 25,
    "viewCount": 17083,
    "likeCount": 124,
    "dislikeCount": 26,
    "relevantKeywords": [
        "black",
        "money",
        "turns",
        "white",
        "economist",
        "jagdish",
        "bhagwati",
        "says",
        "good",
        "ndtv",
        "around",
        "37",
        "000",
        "crores",
        "deposited",
        "jan",
        "dhan",
        "accounts",
        "since",
        "demonetisation",
        "deposits",
        "raised",
        "concern",
        "laundered",
        "using",
        "renowned",
        "however",
        "feels",
        "cause",
        "benefitting",
        "poor",
        "speaking",
        "columbia",
        "university",
        "mr",
        "said",
        "call",
        "corruption",
        "treat",
        "like",
        "amnesty",
        "scheme",
        "watch",
        "videos",
        "download",
        "news",
        "app",
        "narendra",
        "modi",
        "rs",
        "500",
        "1000",
        "notes",
        "banned",
        "cash",
        "crisis",
        "crunch",
        "impact",
        "buck",
        "stops",
        "24x7",
        "little",
        "month",
        "prime",
        "minister",
        "announced",
        "decision",
        "monetize",
        "86",
        "currency",
        "circulation",
        "rupee",
        "debate",
        "india",
        "rages",
        "master",
        "stroke",
        "misadventure",
        "joining",
        "us",
        "somebody",
        "course",
        "well",
        "respected",
        "also",
        "one",
        "foremost",
        "thinkers",
        "public",
        "intellectuals",
        "time",
        "professor",
        "ghibli",
        "geography",
        "welcome",
        "program",
        "first",
        "asked",
        "big",
        "picture",
        "impression",
        "disruptive",
        "people",
        "called",
        "bold",
        "others",
        "absolutely",
        "sense",
        "bad",
        "economy",
        "see",
        "sir",
        "distinguish",
        "avoidable",
        "losses",
        "unavoidable",
        "may",
        "result",
        "instance",
        "print",
        "large",
        "numbers",
        "going",
        "replacing",
        "thousand",
        "actually",
        "order",
        "huge",
        "things",
        "way",
        "could",
        "keep",
        "quiet",
        "bound",
        "know",
        "mean",
        "particular",
        "nothing",
        "kept",
        "secret",
        "long",
        "given",
        "start",
        "printing",
        "ahead",
        "leak",
        "create",
        "massive",
        "disruption",
        "um",
        "transitional",
        "loss",
        "short",
        "run",
        "different",
        "something",
        "think",
        "measure",
        "taken",
        "coming",
        "government",
        "would",
        "come",
        "saying",
        "idea",
        "simply",
        "look",
        "wonder",
        "anybody",
        "looks",
        "degree",
        "care",
        "promise",
        "pay",
        "recon",
        "arrests",
        "pointed",
        "wrong",
        "opinion",
        "amounts",
        "abrogation",
        "obligation",
        "take",
        "note",
        "back",
        "anywhere",
        "rbi",
        "wherever",
        "exchanged",
        "present",
        "give",
        "another",
        "cockeyed",
        "say",
        "sort",
        "talking",
        "violation",
        "right",
        "property",
        "go",
        "gon",
        "na",
        "indian",
        "constitution",
        "taught",
        "years",
        "amendment",
        "passed",
        "enable",
        "impound",
        "social",
        "sometimes",
        "taking",
        "pick",
        "piece",
        "necessary",
        "compensation",
        "point",
        "abolition",
        "person",
        "prep",
        "pretty",
        "versus",
        "princes",
        "struck",
        "gut",
        "supreme",
        "court",
        "kind",
        "notion",
        "somehow",
        "undemocratic",
        "seem",
        "make",
        "kinds",
        "criticisms",
        "view",
        "shoot",
        "hip",
        "problems",
        "worry",
        "let",
        "ask",
        "talk",
        "problematic",
        "seen",
        "data",
        "six",
        "percent",
        "estimated",
        "might",
        "period",
        "phase",
        "discomfort",
        "worth",
        "end",
        "achieve",
        "much",
        "fact",
        "pose",
        "problem",
        "trying",
        "masses",
        "hordes",
        "old",
        "mirrors",
        "lying",
        "used",
        "transact",
        "want",
        "sell",
        "house",
        "difficult",
        "demand",
        "return",
        "paint",
        "rather",
        "write",
        "prepared",
        "even",
        "structural",
        "difficulties",
        "eliminate",
        "possible",
        "holes",
        "holding",
        "swiss",
        "abroad",
        "catch",
        "tell",
        "foreign",
        "light",
        "whether",
        "names",
        "directly",
        "put",
        "yeah",
        "supposing",
        "name",
        "wikileaks",
        "easier",
        "done",
        "feeling",
        "margin",
        "meaning",
        "additionally",
        "really",
        "originate",
        "better",
        "outflows",
        "already",
        "current",
        "bigger",
        "agree",
        "friend",
        "dr",
        "manmohan",
        "singh",
        "stood",
        "parliament",
        "shave",
        "least",
        "accept",
        "accurate",
        "assessment",
        "always",
        "based",
        "assumptions",
        "thing",
        "mine",
        "doubtless",
        "criticize",
        "making",
        "assumption",
        "myra",
        "frank",
        "ideological",
        "congress",
        "party",
        "lost",
        "ways",
        "country",
        "united",
        "states",
        "democrats",
        "donald",
        "trump",
        "yes",
        "damnedest",
        "best",
        "sorts",
        "outcome",
        "accepted",
        "led",
        "monumental",
        "true",
        "member",
        "though",
        "wish",
        "fairly",
        "complicated",
        "issue",
        "interview",
        "study",
        "ramifications",
        "necessarily",
        "gotten",
        "certainly",
        "rushing",
        "pronouncements",
        "former",
        "rushed",
        "within",
        "province",
        "advice",
        "matter",
        "chidambaram",
        "hold",
        "high",
        "regard",
        "political",
        "types",
        "viewing",
        "grain",
        "salt",
        "calling",
        "makers",
        "example",
        "fair",
        "amount",
        "five",
        "hundred",
        "convert",
        "without",
        "bank",
        "detective",
        "servant",
        "rupees",
        "30",
        "scenario",
        "inactive",
        "aisle",
        "mirror",
        "become",
        "active",
        "guy",
        "guard",
        "real",
        "spend",
        "two",
        "effects",
        "redistribution",
        "rich",
        "laundering",
        "happened",
        "judge",
        "sergeant",
        "basically",
        "specific",
        "ready",
        "beneficiaries",
        "means",
        "terms",
        "case",
        "maybe",
        "transacted",
        "transactions",
        "activated",
        "spent",
        "expect",
        "expansionary",
        "effect",
        "deflationary",
        "still",
        "getting",
        "rid",
        "road",
        "stock",
        "decimating",
        "far",
        "destructs",
        "loses",
        "fine",
        "schemes",
        "world",
        "bother",
        "okay",
        "banks",
        "monetization",
        "nearly",
        "12",
        "lakh",
        "value",
        "pi",
        "fourteen",
        "three",
        "overestimated",
        "system",
        "market",
        "parallel",
        "turn",
        "essentially",
        "object",
        "objecting",
        "universally",
        "tried",
        "contexts",
        "lot",
        "printed",
        "either",
        "brought",
        "leaking",
        "astonishing",
        "sphere",
        "15",
        "eleven",
        "half",
        "december",
        "converted",
        "sign",
        "success",
        "culture",
        "etcetera",
        "full",
        "speed",
        "agencies",
        "blast",
        "embarrass",
        "sabotage",
        "secrecy",
        "longer",
        "required",
        "destroys",
        "aim",
        "achieved",
        "exactly",
        "enables",
        "giving",
        "principal",
        "use",
        "help",
        "queue",
        "redistributive",
        "populism",
        "away",
        "wonderful",
        "oh",
        "four",
        "majority",
        "uprising",
        "test",
        "error",
        "sample",
        "survey",
        "happy",
        "benefiting",
        "democratic",
        "artists",
        "despotic",
        "clearly",
        "forget",
        "ji",
        "dan",
        "thourough",
        "politicians",
        "interruption",
        "statements",
        "option",
        "part",
        "circumspect",
        "fail",
        "biggest",
        "everything",
        "observed",
        "daily",
        "wage",
        "laborers",
        "suffering",
        "farmers",
        "labor",
        "works",
        "fields",
        "small",
        "medium",
        "enterprises",
        "hurt",
        "report",
        "jobs",
        "hittin",
        "major",
        "hit",
        "worries",
        "implemented",
        "concerns",
        "implementation",
        "lack",
        "head",
        "delays",
        "able",
        "answer",
        "question",
        "sure",
        "pumped",
        "nandan",
        "nilekani",
        "compensate",
        "withdrawn",
        "smooth",
        "transition",
        "shortage",
        "secondly",
        "buy",
        "studied",
        "decades",
        "tend",
        "rush",
        "judgment",
        "export",
        "markets",
        "worried",
        "closed",
        "open",
        "crazy",
        "rules",
        "made",
        "available",
        "rapidly",
        "soon",
        "get",
        "bureaucrat",
        "decent",
        "bureaucrats",
        "consulted",
        "forte",
        "need",
        "man",
        "men",
        "practical",
        "experience",
        "women",
        "lived",
        "briefly",
        "governor",
        "ajit",
        "patel",
        "appointed",
        "among",
        "welcomed",
        "choice",
        "focus",
        "feel",
        "upfront",
        "visible",
        "authority",
        "undermined",
        "critics",
        "today",
        "last",
        "thoughts",
        "comes",
        "background",
        "stupid",
        "wanted",
        "length",
        "inference",
        "suddenly",
        "came",
        "blue",
        "told",
        "economists",
        "driving",
        "force",
        "security",
        "pakistan",
        "possibly",
        "lots",
        "counterfeit",
        "apparently",
        "many",
        "friends",
        "ground",
        "blame",
        "smart",
        "jit",
        "moved",
        "quickly",
        "bit",
        "unfair",
        "got",
        "started",
        "tweaking",
        "trust",
        "fix",
        "arising",
        "america",
        "monday",
        "morning",
        "quarterbacking",
        "event",
        "ah",
        "thought",
        "policy",
        "consists",
        "infeasible",
        "art",
        "anticipating",
        "every",
        "move",
        "arise",
        "tweak",
        "income",
        "tax",
        "act",
        "november",
        "28th",
        "changes",
        "8th",
        "maker",
        "anticipate",
        "particularly",
        "gigantic",
        "undertaken",
        "develop",
        "mark",
        "poverty",
        "thinking",
        "guessing",
        "thumbs",
        "caused",
        "pleasure",
        "thank",
        "martha"
    ]
}